[{"symbol":"PENGUUSDT","contract":"2zMMhcVQEXDtdE6vsFS7S7D5oUodfJHE8vd1gnBouauv","baseCoin":"PENGU","quoteCoin":"USDT","lastPrice":{"bybit":0.0066,"okx":0.006595,"mexc":0,"jupiter":0.006604846661719733},"spread":{"bybit":0.08,"okx":0},"bidPrice":{"bybit":0.00659,"okx":0.006601,"mexc":0,"jupiter":0},"bidSize":{"bybit":2810887,"okx":25176,"mexc":0,"jupiter":0},"askPrice":{"bybit":0.00661,"okx":0.006605,"mexc":0,"jupiter":0},"askSize":{"bybit":1399298,"okx":51493,"mexc":0,"jupiter":0}},{"symbol":"TRUMPUSDT","contract":"6p6xgHyF7AeE6TZkSmFsko444wqoP15icUSqi2jfGiPN","baseCoin":"TRUMP","quoteCoin":"USDT","lastPrice":{"bybit":13.41,"okx":13.405,"mexc":0,"jupiter":13.423468867318835},"spread":{"bybit":0.04,"okx":0},"bidPrice":{"bybit":13.4,"okx":13.403,"mexc":0,"jupiter":0},"bidSize":{"bybit":275.21,"okx":44.8834,"mexc":0,"jupiter":0},"askPrice":{"bybit":13.41,"okx":13.405,"mexc":0,"jupiter":0},"askSize":{"bybit":351.34,"okx":26.3854,"mexc":0,"jupiter":0}},{"symbol":"BOMEUSDT","contract":"ukHH6c7mMyiWCf1b9pnWe25TSpkDDt3H5pQZgZ74J82","baseCoin":"BOME","quoteCoin":"USDT","lastPrice":{"bybit":0.001682,"okx":0.001682,"mexc":0,"jupiter":0.0016871411056197036},"spread":{"bybit":0,"okx":0},"bidPrice":{"bybit":0.001681,"okx":0.001681,"mexc":0,"jupiter":0},"bidSize":{"bybit":277765.82,"okx":40500,"mexc":0,"jupiter":0},"askPrice":{"bybit":0.001682,"okx":0.001682,"mexc":0,"jupiter":0},"askSize":{"bybit":400000,"okx":260692,"mexc":0,"jupiter":0}},{"symbol":"ZEREBROUSDT","contract":"8x5VqbHA8D7NkD52uNuS5nnt3PwA8pLD34ymskeSo2Wn","baseCoin":"ZEREBRO","quoteCoin":"USDT","lastPrice":{"bybit":0.0421,"okx":0,"mexc":0,"jupiter":0.042040270174589424},"spread":{"bybit":0,"okx":0},"bidPrice":{"bybit":0.0421,"okx":0,"mexc":0,"jupiter":0},"bidSize":{"bybit":57758.5,"okx":0,"mexc":0,"jupiter":0},"askPrice":{"bybit":0.0422,"okx":0,"mexc":0,"jupiter":0},"askSize":{"bybit":32916.3,"okx":0,"mexc":0,"jupiter":0}}]